html_css_gen/__init__.py
html_css_gen/template.py
html_css_gen-2.2.1.dist-info/LICENSE
html_css_gen-2.2.1.dist-info/METADATA
html_css_gen-2.2.1.dist-info/WHEEL
html_css_gen-2.2.1.dist-info/top_level.txt
html_css_gen-2.2.1.dist-info/RECORD
