Metadata-Version: 2.1
Name: html-css-gen
Version: 2.2.1
Summary: snippet to merge html/css files
Home-page: https://bitbucket.org/guangyong/html_css_gen/
Author: guangyong
Author-email: guangyong@live.com
License: UNKNOWN
Platform: UNKNOWN
Classifier: Programming Language :: Python :: 3
Classifier: License :: OSI Approved :: MIT License
Classifier: Operating System :: OS Independent
